RequestParser/__init__.py
RequestParser/requestParser.py
RequestParser-2024.1.0.dist-info/METADATA
RequestParser-2024.1.0.dist-info/WHEEL
RequestParser-2024.1.0.dist-info/top_level.txt
RequestParser-2024.1.0.dist-info/RECORD
