Metadata-Version: 2.1
Name: RequestParser
Version: 2024.1.0
Summary: Parse the raw HTTP Request
Home-page: UNKNOWN
Author: dyn.lee
Author-email: duyenle.201001@gmail.com
License: UNKNOWN
Keywords: HTTP Request Parser
Platform: UNKNOWN
Classifier: Programming Language :: Python :: 3
